[
  {
    "agent": "Learner",
    "action": "learn_from_fixes",
    "timestamp": 1749031452.4128926,
    "details": {
      "count": 1
    }
  },
  {
    "agent": "Monitor",
    "action": "check_health",
    "timestamp": 1749031452.4154866,
    "details": {}
  },
  {
    "agent": "Monitor",
    "action": "raise_alert",
    "timestamp": 1749031452.9172156,
    "details": {
      "type": "system",
      "component": "disk",
      "severity": "medium",
      "message": "Disk usage is high: 94.9%"
    }
  },
  {
    "agent": "Monitor",
    "action": "raise_alert",
    "timestamp": 1749031452.9173527,
    "details": {
      "type": "memory",
      "component": "backup",
      "severity": "low",
      "message": "No memory backups found"
    }
  },
  {
    "agent": "TestGenerator",
    "action": "generate_tests",
    "timestamp": 1749031452.9226923,
    "details": {
      "count": 1,
      "complexity": "beginner"
    }
  },
  {
    "agent": "Tester",
    "action": "run_tests",
    "timestamp": 1749031458.861093,
    "details": {
      "count": 1
    }
  },
  {
    "agent": "Fixer",
    "action": "fix_issues",
    "timestamp": 1749031459.8654099,
    "details": {
      "count": 1
    }
  },
  {
    "agent": "Learner",
    "action": "learn_from_fixes",
    "timestamp": 1749031511.9368804,
    "details": {
      "count": 1
    }
  },
  {
    "agent": "Monitor",
    "action": "check_health",
    "timestamp": 1749031511.9394572,
    "details": {}
  },
  {
    "agent": "Monitor",
    "action": "raise_alert",
    "timestamp": 1749031512.4408689,
    "details": {
      "type": "system",
      "component": "disk",
      "severity": "medium",
      "message": "Disk usage is high: 94.9%"
    }
  }
]