[
  {
    "agent": "Monitor",
    "action": "check_health",
    "timestamp": 1749030191.5331297,
    "details": {}
  },
  {
    "agent": "Monitor",
    "action": "raise_alert",
    "timestamp": 1749030192.0343492,
    "details": {
      "type": "system",
      "component": "disk",
      "severity": "medium",
      "message": "Disk usage is high: 94.9%"
    }
  },
  {
    "agent": "Monitor",
    "action": "raise_alert",
    "timestamp": 1749030192.0344446,
    "details": {
      "type": "memory",
      "component": "backup",
      "severity": "low",
      "message": "No memory backups found"
    }
  },
  {
    "agent": "TestGenerator",
    "action": "generate_tests",
    "timestamp": 1749030192.0378208,
    "details": {
      "count": 1,
      "complexity": "beginner"
    }
  },
  {
    "agent": "Tester",
    "action": "run_tests",
    "timestamp": 1749030200.5394232,
    "details": {
      "count": 1
    }
  },
  {
    "agent": "Fixer",
    "action": "fix_issues",
    "timestamp": 1749030202.5435362,
    "details": {
      "count": 1
    }
  },
  {
    "agent": "Learner",
    "action": "learn_from_fixes",
    "timestamp": 1749030207.0852017,
    "details": {
      "count": 1
    }
  },
  {
    "agent": "Monitor",
    "action": "check_health",
    "timestamp": 1749030237.0887227,
    "details": {}
  },
  {
    "agent": "Monitor",
    "action": "raise_alert",
    "timestamp": 1749030237.5900154,
    "details": {
      "type": "system",
      "component": "disk",
      "severity": "medium",
      "message": "Disk usage is high: 94.9%"
    }
  },
  {
    "agent": "Monitor",
    "action": "raise_alert",
    "timestamp": 1749030237.5901392,
    "details": {
      "type": "memory",
      "component": "backup",
      "severity": "low",
      "message": "No memory backups found"
    }
  }
]